example_test/__init__.py
example_test/test.py
example_test_20240902/__init__.py
example_test_20240902/test.py
example_test_20240902-0.2.dist-info/METADATA
example_test_20240902-0.2.dist-info/WHEEL
example_test_20240902-0.2.dist-info/top_level.txt
example_test_20240902-0.2.dist-info/RECORD
