Metadata-Version: 2.1
Name: example_test_20240902
Version: 0.2
Summary: for explain about pypi deploy
Home-page: 
Download-URL: 
Author: test
Author-email: test@test.com
Keywords: pypideploy
Classifier: Programming Language :: Python :: 3
Classifier: Programming Language :: Python :: 3.2
Classifier: Programming Language :: Python :: 3.3
Classifier: Programming Language :: Python :: 3.4
Classifier: Programming Language :: Python :: 3.5
Classifier: Programming Language :: Python :: 3.6
Classifier: Programming Language :: Python :: 3.7
Requires-Python: >=3
